[
  {
    "name": "Schlafzimmer",
    "coordinates": [
      [
        19724,
        22129,
        22725,
        26371,
        1
      ]
    ]
  },
  {
    "name": "Küche",
    "coordinates": [
      [
        32610,
        20848,
        34673,
        22149,
        1
      ]
    ]
  },
  {
    "name": "Arbeitszimmer",
    "coordinates": [
      [
        25067,
        23339,
        28467,
        26482,
        1
      ]
    ]
  },
  {
    "name": "Essbereich",
    "coordinates": [
      [
        35282,
        20373,
        38636,
        23412,
        1
      ],
      [
        32726,
        22205,
        35289,
        23387,
        1
      ]
    ]
  },
  {
    "name": "Eingangsbereich",
    "coordinates": [
      [
        23369,
        21610,
        26878,
        23200,
        1
      ]
    ]
  },
  {
    "name": "Flur",
    "coordinates": [
      [
        23377,
        22062,
        32681,
        23277,
        1
      ],
      [
        23888,
        21204,
        27676,
        22027,
        1
      ]
    ]
  },
  {
    "name": "Kinderzimmer",
    "coordinates": [
      [
        28534,
        23414,
        31989,
        26564,
        1
      ]
    ]
  },
  {
    "name": "Wohnzimmer",
    "coordinates": [
      [
        32662,
        23340,
        36457,
        26554,
        1
      ]
    ]
  },
  {
    "name": "Ensuite-Bad",
    "coordinates": [
      [
        22849,
        24110,
        24614,
        26475,
        1
      ]
    ]
  },
  {
    "name": "Bad",
    "coordinates": [
      [
        28692,
        20212,
        31568,
        22028,
        1
      ]
    ]
  }
]